LICENSE
README.md
setup.py
TB2J_OpenMX/__init__.py
TB2J_OpenMX/ffimod.py
TB2J_OpenMX/ffiparser.py
TB2J_OpenMX/gen_exchange.py
TB2J_OpenMX.egg-info/PKG-INFO
TB2J_OpenMX.egg-info/SOURCES.txt
TB2J_OpenMX.egg-info/dependency_links.txt
TB2J_OpenMX.egg-info/requires.txt
TB2J_OpenMX.egg-info/top_level.txt
TB2J_OpenMX/cmod/__init__.py
scripts/openmx2J.py