Metadata-Version: 2.1
Name: TB2J-OpenMX
Version: 0.5.0
Summary: TB2J_OpenMX: TB2J interface to OpenMX
Home-page: UNKNOWN
Author: Xu He
Author-email: mailhexu@gmail.com
License: GPLv3
Platform: UNKNOWN
Classifier: Development Status :: 3 - Alpha
Classifier: Programming Language :: Python :: 3
Classifier: Intended Audience :: Science/Research
Classifier: Topic :: Scientific/Engineering :: Chemistry
Classifier: Topic :: Scientific/Engineering :: Physics
Requires-Python: >=3.6
License-File: LICENSE
